memory/data_memory.sv
module DataMemory(
    input Clock clk,
    input Addr idx,
    input Data write_data,
    input Bool write_enable,
    output Data read_data_out
);
    DataReg mem[128:0];
    assign read_data_out = mem[idx[9:2]];

    initial begin
        mem[0] = `X1;
        mem[1] = `X2;
    end

    always @ (posedge clk) begin
        if (write_enable == 1) begin
            mem[idx[9:2]] <= write_data;
            $display("MEM: write [%h]=%h", idx, write_data);
         end
    end
endmodule

pipeline/stage_4_mem.sv
module Stage4Mem(
    input Clock clk,
    input Bool stall,
    input Data alu_res,
    input Data rs2_val,
    input RegId rd_idx,
    input Bool mem_load_enable,
    input Bool mem_store_enable,
    input Bool reg_write_enable,

    output BoolReg write_enable_out = FALSE,
    output RegIdReg write_idx_out = 'b0,
    output DataReg write_data_out = 'b0
);
    Data mem_read_data;

    DataMemory dmem(
        .clk(clk),
        .write_enable(mem_store_enable),
        .write_data(rs2_val),
        .idx(alu_res),
        .read_data_out(mem_read_data)
    );

    always @(negedge clk) begin
        // TODO stall
        write_enable_out <= reg_write_enable;
        write_idx_out <= rd_idx;
        write_data_out <= (mem_load_enable) ? mem_read_data : alu_res;
    end
endmodule

alu/alu.sv
module ALU (
    input Data a,
    input Data b,
    input ALUOp op,
    input Bool mod,    // Modifier: used for arithmetic shift
    output DataReg res_out
);
    assign res_out = alu(a, b, op, mod);

    // always @ (a, b, op, mod) begin
    //     $display("ALU: %h -> (%d %d) = %d", op, a, $signed(b), $signed(res_out));
    // end
endmodule

function Data alu(
    input Data a, b,
    input ALUOp op,
    input Bool mod
);
    case (op)
        ADD: alu = a + b;
        SLL: alu = a << b;
        SLT: alu = {{31{1'b0}}, $signed(a) < $signed(b)};
        SLTU: alu = {{31{1'b0}}, a < b};
        XOR: alu = a ^ b;
        SR: alu = (mod) ? (a >>> b) : (a >> b);
        OR: alu = a | b;
        AND: alu = a & b;
    endcase
endfunction

pipeline/stage_3_exec.sv
module Stage3Exec (
    input Clock clk,
    input Bool  stall,
    input ALUOp alu_op,
    input Bool  alu_op_modified,
    input Data  rs1_val,
    input Data  rs2_val,
    input Data  imm,
    input Bool  use_imm,
    input RegId rd_idx,
    input Bool  mem_store_enable,
    input Bool  mem_load_enable,
    input Bool  reg_write_enable,
    input Bool  jump_enable,
    input Bool  branch_enable,
    input Addr  jump_address,

    output DataReg  alu_res_out = 'b0,
    output DataReg  rs2_val_out = 'b0,
    output RegIdReg rd_idx_out = 'b0,
    output BoolReg  jump_enable_out = FALSE,
    output DataReg  jump_address_out = 'b0,
    output BoolReg  mem_store_enable_out = FALSE,
    output BoolReg  mem_load_enable_out = FALSE,
    output BoolReg  reg_write_enable_out = FALSE
);
  Data alu_res;

  ALU alu (
      .a      (rs1_val),
      .b      ((use_imm) ? imm : rs2_val),
      .op     (alu_op),
      .mod    (alu_op_modified),
      .res_out(alu_res)
  );

  always @(negedge clk) begin
    rd_idx_out <= (stall) ? rd_idx_out : rd_idx;
    rs2_val_out <= (stall) ? rs2_val_out : rs2_val;
    mem_load_enable_out <= (stall) ? mem_load_enable_out : mem_load_enable;
    mem_store_enable_out <= (stall) ? mem_store_enable_out : mem_store_enable;
    reg_write_enable_out <= (stall) ? reg_write_enable_out : reg_write_enable;
    alu_res_out <= (stall) ? alu_res_out : alu_res;
    jump_enable_out <= (stall) ? jump_enable_out : (jump_enable || (branch_enable && (alu_op_modified ^ (alu_res == 'b0))));
    jump_address_out <= (stall) ? jump_address_out : jump_address;
  end
endmodule

register/gp_register_file.sv
module GPRegisterFile(
    input wire[0:0] clk,
    input wire[4:0] read_idx_1,
    input wire[4:0] read_idx_2,
    input wire[4:0] write_idx,
    input wire[31:0] write_data,
    input wire[0:0] write_enable,
    output wire[31:0] read_data_1,
    output wire[31:0] read_data_2
);
    DataReg gp[31:0];

    assign read_data_1 = read_gp_with_fwd(read_idx_1);
    assign read_data_2 = read_gp_with_fwd(read_idx_2);

    always @ (posedge clk) begin
        if (write_enable) begin
            if (write_idx != 0) gp[write_idx] <= write_data;
            $display("REG: r1=%h r2=%h w[%d]=%h", gp[1], gp[2], write_idx, write_data);
        end
    end

    function Data read_gp_with_fwd(
        input RegId idx
    );
        if (idx == 0)
            read_gp_with_fwd = 'b0;
        else if (write_enable && idx == write_idx)
            read_gp_with_fwd = write_data;
        else
            read_gp_with_fwd = gp[idx];
    endfunction
endmodule

decode/decode.sv
module Decode(
    input Instr            instruction,
    output DecodeOutput    decoded_out
);    
    // Byteswap to fit specification description
    assign decoded_out = decode(parse(byteswap(instruction)));
endmodule

function bit[31:0] byteswap(input bit[31:0] x);
    byteswap = {x[7:0], x[15:8], x[23:16], x[31:24]};
endfunction

function ParsedInstruction parse(input Instr intruction);
    parse.opcode   = intruction[6:2];       // Assuming only 32bit instruction support
    parse.rd       = intruction[11:7];
    parse.funct3   = intruction[14:12];
    parse.rs1      = intruction[19:15];
    parse.rs2      = intruction[24:20];
    parse.funct7   = intruction[31:25];
    parse.imm_sign = intruction[31];
    parse.I_imm    = {{20{parse.imm_sign}}, parse.funct7, parse.rs2};
    parse.S_imm    = {{20{parse.imm_sign}}, parse.funct7, parse.rd};
    parse.U_imm    = {{12{parse.imm_sign}}, parse.funct7, parse.rs2, parse.rs1, parse.funct3};
    parse.B_imm    = {{20{parse.imm_sign}}, parse.imm_sign, intruction[7], intruction[30:25], intruction[11:8]};
    parse.J_imm    = {{13{parse.imm_sign}}, parse.rs1, parse.funct3, intruction[20], intruction[30:21]};
endfunction

function DecodeOutput decode(input ParsedInstruction i);
    decode = 61'bx;

    case (i.opcode)
        OP: begin
            decode.alu_rs1 = i.rs1;
            decode.alu_rs2 = i.rs2;
            decode.alu_rd = i.rd;
            decode.alu_op = i.funct3;
            decode.alu_use_imm = FALSE;
            decode.alu_rs1_pc = FALSE;
            decode.alu_rs2_neg = (i.funct3 == 'b0 && i.funct7 == 'd32); // Subtraction
            decode.alu_op_mod = FALSE;
            decode.imm = `NONE;
            decode.mem_load = FALSE;
            decode.mem_store = FALSE;
            decode.reg_write = TRUE;
            decode.jump_enable = FALSE;
            decode.branch_enable = FALSE;
            decode.debug = OK;
            $display("DEC: ALURegOp %h (%h <= %h %h)", i.funct3, i.rd, i.rs1, i.rs2);
        end
        OP_IMM: begin
            decode.alu_rs1 = i.rs1;
            decode.alu_rs2 = 'b0;
            decode.alu_rd = i.rd;
            decode.alu_op = i.funct3;
            decode.alu_use_imm = TRUE;
            decode.alu_rs1_pc = FALSE;
            decode.alu_rs2_neg = (i.funct3 == 'b0 && i.funct7 == 'd32); // Subtraction
            decode.alu_op_mod = FALSE;
            decode.imm = i.I_imm;
            decode.mem_load = FALSE;
            decode.mem_store = FALSE;
            decode.reg_write = TRUE;
            decode.jump_enable = FALSE;
            decode.branch_enable = FALSE;
            decode.debug = OK;
            $display("DEC: ALUImmOp %h (%h <= %h %h)", i.funct3, i.rd, i.rs1, i.I_imm);
        end
        LOAD: begin
            decode.alu_rs1 = i.rs1;
            decode.alu_rs2 = 'b0;
            decode.alu_rd = i.rd;
            decode.alu_op = 'h0;
            decode.alu_use_imm = TRUE;
            decode.alu_rs1_pc = FALSE;
            decode.alu_rs2_neg = FALSE;
            decode.alu_op_mod = FALSE;
            decode.imm = i.I_imm;
            decode.mem_load = TRUE;
            decode.mem_store = FALSE;
            decode.reg_write = TRUE;
            decode.jump_enable = FALSE;
            decode.branch_enable = FALSE;
            decode.debug = OK;
            $display("DEC: Load %h => %h+%h", i.rd, i.rs1, i.I_imm);
        end
        STORE: begin
            decode.alu_rs1 = i.rs1;
            decode.alu_rs2 = i.rs2;
            decode.alu_rd = i.rd;
            decode.alu_op = 'h0;
            decode.alu_use_imm = TRUE;
            decode.alu_rs1_pc = FALSE;
            decode.alu_rs2_neg = FALSE;
            decode.alu_op_mod = FALSE;
            decode.imm = i.S_imm;    // Offset to rs1
            decode.mem_load = FALSE;
            decode.mem_store = TRUE;
            decode.reg_write = FALSE;
            decode.jump_enable = FALSE;
            decode.branch_enable = FALSE;
            decode.debug = OK;
            $display("DEC: Store %h => %h+%h", i.rs2, i.rs1, i.I_imm);
        end
        JAL: begin
            decode.alu_rs1 = 'b0;
            decode.alu_rs2 = 'b0;
            decode.alu_rd = i.rd;
            decode.alu_op = 'h4;
            decode.alu_use_imm = FALSE;
            decode.alu_rs1_pc = TRUE;
            decode.alu_rs2_neg = FALSE;
            decode.alu_op_mod = FALSE;
            decode.imm = i.J_imm << 1;
            decode.mem_load = FALSE;
            decode.mem_store = FALSE;
            decode.reg_write = TRUE;
            decode.jump_enable = TRUE;
            decode.branch_enable = FALSE;
            decode.debug = OK;
            $display("DEC: Jump %h, %d", i.J_imm, $signed(i.J_imm));
        end
        BRANCH: begin
            decode.alu_rs1 = i.rs1;
            decode.alu_rs2 = i.rs2;
            decode.alu_rd = 'h0;
            decode.alu_op = {1'b0, i.funct3[2:1]};
            decode.alu_rs2_neg = ~i.funct3[2];
            decode.alu_op_mod = i.funct3[0];
            decode.alu_use_imm = FALSE;
            decode.alu_rs1_pc = FALSE;
            decode.imm = i.B_imm << 1;
            decode.mem_load = FALSE;
            decode.mem_store = FALSE;
            decode.reg_write = FALSE;
            decode.jump_enable = FALSE;
            decode.branch_enable = TRUE;
            decode.debug = OK;
            $display("DEC: Branch by %h", $signed(i.B_imm << 1));
        end
        SYSTEM: begin
            decode.alu_rs1 = 'b0;
            decode.alu_rs2 = 'b0;
            decode.alu_rd = 'b0;
            decode.alu_rs1_pc = FALSE;
            decode.alu_op_mod = FALSE;
            decode.reg_write = FALSE;
            decode.jump_enable = FALSE;
            decode.branch_enable = FALSE;
            case ({i.funct7, i.rs2, i.rs1, i.funct3, i.rd})
                25'b0000000_00001_00000_000_00000: decode.debug = BREAK;
                default: decode.debug = FAIL;
            endcase
            $display("DEC: System instruction invoked");
        end
        default: begin
            decode.alu_rs1 = 'b0;
            decode.alu_rs2 = 'b0;
            decode.alu_rd = 'b0;
            decode.alu_rs1_pc = FALSE;
            decode.alu_op_mod = FALSE;
            decode.reg_write = FALSE;
            decode.jump_enable = FALSE;
            decode.branch_enable = FALSE;
            decode.debug = FAIL;
            $display("DEC: Unknown instruction");
        end
    endcase
endfunction

pipeline/stage_2_decode.sv
module Stage2Decode (
    input  Clock       clk,
    input  Bool        stall,
    input  Data        instruction,
    input  Data        pc,
    input  Bool        write_enable,
    input  RegId       write_idx,
    input  Data        write_data,
    output ALUOpReg    alu_op = 'b0,
    output DataReg     rs1_val = 'b0,
    output DataReg     rs2_val = 'b0,
    output DataReg     imm = 'b0,
    output BoolReg     use_imm = FALSE,
    output RegIdReg    rd_idx = 'b0,
    output BoolReg     alu_op_mod = FALSE,
    output BoolReg     mem_load_enable = FALSE,
    output BoolReg     mem_store_enable = FALSE,
    output BoolReg     jump_enable = FALSE,
    output BoolReg     branch_enable = FALSE,
    output BoolReg     reg_write_enable = FALSE,
    output AddrReg     jump_address = 'b0,
    output DebugStatus debug = OK
);
  RegId rs1_idx, rs2_idx;
  Bool rs1_use_pc, rs2_neg;
  Data rs1_val_wire, rs2_val_wire;

  DecodeOutput decoded;

  Decode decode (
      .instruction(instruction),
      .decoded_out(decoded)
  );


  GPRegisterFile gpr (
      .clk         (clk),
      .read_idx_1  (decoded.alu_rs1),
      .read_idx_2  (decoded.alu_rs2),
      .read_data_1 (rs1_val_wire),
      .read_data_2 (rs2_val_wire),
      .write_enable(write_enable),
      .write_idx   (write_idx),
      .write_data  (write_data)
  );

  always @(negedge clk) begin
    alu_op <= (stall) ? alu_op : decoded.alu_op;
    rs1_val <= (stall) ? rs1_val : ((decoded.alu_rs1_pc) ? pc : rs1_val_wire);
    rs2_val <= (stall) ? rs2_val : ((decoded.alu_rs2_neg) ? -$signed(rs2_val_wire) : rs2_val_wire);
    imm <= (stall) ? imm : decoded.imm;
    use_imm <= (stall) ? use_imm : decoded.alu_use_imm;
    rd_idx <= (stall) ? rd_idx : decoded.alu_rd;
    alu_op_mod <= (stall) ? alu_op_mod : decoded.alu_op_mod;
    jump_address <= (stall) ? jump_address : pc + $signed(decoded.imm);
    jump_enable <= (stall) ? jump_enable : decoded.jump_enable;
    branch_enable <= (stall) ? branch_enable : decoded.branch_enable;
    reg_write_enable <= (stall) ? reg_write_enable : decoded.reg_write;
    mem_load_enable <= (stall) ? mem_load_enable : decoded.mem_load;
    mem_store_enable <= (stall) ? mem_store_enable : decoded.mem_store;
    debug <= (stall) ? debug : decoded.debug;
  end
endmodule

memory/instruction_memory.sv
module InstructionMemory(
    input Addr address,
    output Addr instruction_out
);
    DataReg mem[128:0];
    integer fd, i;

    assign instruction_out = mem[address[9:2]];

    initial begin
        fd = $fopen("gcd.bin","rb");
        i = $fread(mem, fd);
        $fclose(fd);
    end
endmodule

register/program_counter.sv
module ProgramCounter(
    input Clock clk,
    input Bool jump_enable,
    input Addr jump_address,
    output Addr address_out,
    output Addr next_address_out
);
    AddrReg pc = 'b0;

    assign next_address_out = pc + 'd4;
    assign address_out = pc;
    
    always @ (posedge clk) begin
        pc <= (jump_enable) ? jump_address : next_address_out;
        // $display("====================================================");
        // $display("PC: 0x%h [jump=%h]", (jump_enable) ? jump_address : next_address_out, jump_enable);
    end

endmodule

pipeline/stage_1_fetch.sv
module Stage1Fetch(
    input wire[0:0] clk,
    input wire[0:0] stall,
    input wire [0:0] jump_enable,
    input wire[31:0] jump_address,
    output reg[31:0] instruction = 'b0010011000000000000000000000000, // NOP
    output reg[31:0] next_address = 'b0
);
    wire [31:0] address, intruction_wire, next_address_wire;

    ProgramCounter pc(
        .clk(clk),
        .jump_enable(jump_enable),
        .jump_address(jump_address),
        .address_out(address),
        .next_address_out(next_address_wire)
    );

    InstructionMemory imem(
        .address(address),
        .instruction_out(intruction_wire)
    );

    always @(negedge clk) begin
        instruction <= (stall) ? instruction : intruction_wire;
        next_address <= (stall) ? next_address : next_address_wire;
    end

endmodule

test_pipeline_cpu.sv
typedef bit [31:0] Data;
typedef reg [31:0] DataReg;
typedef bit [0:0] Clock;
typedef bit [31:0] Addr;
typedef reg [31:0] AddrReg;
typedef bit [31:0] Instr;
typedef reg [31:0] InstrReg;
typedef bit [4:0] RegId;
typedef reg [4:0] RegIdReg;

enum bit [4:0] {
  OP = 'b01100,
  OP_IMM = 'b00100,
  SYSTEM = 'b11100,
  LOAD = 'b00000,
  STORE = 'b01000,
  JAL = 'b11011,
  BRANCH = 'b11000
} Opcode;

typedef enum bit [2:0] {
  ADD = 'h0,
  SLL = 'h1,
  SLT = 'h2,
  SLTU = 'h3,
  XOR = 'h4,
  SR = 'h5,
  OR = 'h6,
  AND = 'h7
} ALUOp;

typedef bit [2:0] ALUOpReg;

typedef enum bit [1:0] {
  OK = 2'b00,
  BREAK = 2'b01,
  FAIL = 2'b10
} DebugStatus;

typedef enum bit [0:0] {
  FALSE = 1'b0,
  TRUE = 1'b1
} Bool;

typedef reg [0:0] BoolReg;

typedef struct packed {
  ALUOp alu_op;
  RegId alu_rs1;
  RegId alu_rs2;
  RegId alu_rd;
  Bool alu_use_imm;
  Bool alu_rs1_pc;
  Bool alu_rs2_neg;
  Bool alu_op_mod;
  Data imm;
  Bool mem_load;
  Bool mem_store;
  Bool reg_write;
  Bool jump_enable;
  Bool branch_enable;
  DebugStatus debug;
} DecodeOutput;

`define NONE 'bx

typedef struct packed {
  bit [4:0] opcode;
  bit [6:0] funct7;
  bit [2:0] funct3;
  bit [4:0] rs1, rs2, rd;
  bit [0:0] imm_sign;
  bit [31:0] I_imm, S_imm, U_imm, B_imm, J_imm;
} ParsedInstruction;

module test ();
  reg Clock clk;

  // 1 -> 2
  wire Instr intruction_12;
  wire Addr next_address_12;
  // 3 -> 1
  wire Bool jump_enable_31;
  wire Addr jump_address_31;

  Stage1Fetch s1 (
      .clk         (clk),
      .stall       (1'b0),
      // 1 -> 2
      .instruction (intruction_12),
      .next_address(next_address_12),
      .jump_enable (jump_enable_31),
      .jump_address(jump_address_31)
  );

  // 2 -> 3
  wire Data rs1_val_23, rs2_val_23, imm_23;
  wire RegId rd_idx_23;
  wire ALUOp alu_op_23;
  wire Bool use_imm_23, alu_op_mod_23, mem_load_enable_23, mem_store_enable_23,
      reg_write_enable_23, branch_enable_23;
  wire Addr jump_address_23;
  // 4 -> 2
  wire Data write_data_42;
  wire RegId write_idx_42;
  wire Bool write_enable_42;

  wire DebugStatus debug;

  Stage2Decode s2 (
      .clk             (clk),
      .stall           (1'b0),
      // 1 -> 2
      .instruction     (intruction_12),
      .pc              (next_address_12),
      // 2 -> 3
      .alu_op          (alu_op_23),
      .rs1_val         (rs1_val_23),
      .rs2_val         (rs2_val_23),
      .rd_idx          (rd_idx_23),
      .imm             (imm_23),
      .use_imm         (use_imm_23),
      .alu_op_mod      (alu_op_mod_23),
      .mem_load_enable (mem_load_enable_23),
      .mem_store_enable(mem_store_enable_23),
      .reg_write_enable(reg_write_enable_23),
      .jump_enable     (jump_enable_23),
      .branch_enable   (branch_enable_23),
      .jump_address    (jump_address_23),
      // 4 -> 2
      .write_data      (write_data_42),
      .write_idx       (write_idx_42),
      .write_enable    (write_enable_42),

      .debug(debug)
  );

  // 3 -> 4
  wire Data alu_res_34, rs2_val_34;
  wire RegId rd_idx_34;
  wire Bool mem_store_enable_34, mem_load_enable_34, reg_write_enable_34;

  Stage3Exec s3 (
      .clk                 (clk),
      .stall               (1'b0),
      // 2 -> 3
      .alu_op              (alu_op_23),
      .rs1_val             (rs1_val_23),
      .rs2_val             (rs2_val_23),
      .imm                 (imm_23),
      .rd_idx              (rd_idx_23),
      .alu_op_modified     (alu_op_mod_23),
      .use_imm             (use_imm_23),
      .reg_write_enable    (reg_write_enable_23),
      .mem_load_enable     (mem_load_enable_23),
      .mem_store_enable    (mem_store_enable_23),
      .jump_enable         (jump_enable_23),
      .jump_address        (jump_address_23),
      .branch_enable       (branch_enable_23),
      // 3 -> 4
      .alu_res_out         (alu_res_34),
      .rs2_val_out         (rs2_val_34),
      .rd_idx_out          (rd_idx_34),
      .reg_write_enable_out(reg_write_enable_34),
      .mem_load_enable_out (mem_load_enable_34),
      .mem_store_enable_out(mem_store_enable_34),
      .jump_enable_out     (jump_enable_31),
      .jump_address_out    (jump_address_31)
  );

  Stage4Mem s4 (
      .clk             (clk),
      .stall           (1'b0),
      // 3 -> 4
      .alu_res         (alu_res_34),
      .rs2_val         (rs2_val_34),
      .rd_idx          (rd_idx_34),
      .reg_write_enable(reg_write_enable_34),
      .mem_load_enable (mem_load_enable_34),
      .mem_store_enable(mem_store_enable_34),
      // 4 -> 2
      .write_enable_out(write_enable_42),
      .write_idx_out   (write_idx_42),
      .write_data_out  (write_data_42)
  );


  always @(debug) begin
    case (debug)
      'b01: begin
        $display("Breakpoint reached");
        $finish;
      end
      'b10: begin
        $display("Illegal instruction - teminating");
        $finish;
      end
    endcase
  end

  initial begin
    $dumpfile("test.vcd");
    $dumpvars;
    clk = 0;
  end

  always #2 begin
    clk = ~clk;
  end
  always #10000 $finish; // Terminate the program in case of infinite loop
endmodule

test.vcd
$date
	Wed Jan  6 23:27:09 2021
$end
$version
	Icarus Verilog
$end
$timescale
	1s
$end
$scope module test $end
$var wire 5 ! write_idx_42 [4:0] $end
$var wire 1 " write_enable_42 $end
$var wire 32 # write_data_42 [31:0] $end
$var wire 1 $ use_imm_23 $end
$var wire 32 % rs2_val_34 [31:0] $end
$var wire 32 & rs2_val_23 [31:0] $end
$var wire 32 ' rs1_val_23 [31:0] $end
$var wire 1 ( reg_write_enable_34 $end
$var wire 1 ) reg_write_enable_23 $end
$var wire 5 * rd_idx_34 [4:0] $end
$var wire 5 + rd_idx_23 [4:0] $end
$var wire 32 , next_address_12 [31:0] $end
$var wire 1 - mem_store_enable_34 $end
$var wire 1 . mem_store_enable_23 $end
$var wire 1 / mem_load_enable_34 $end
$var wire 1 0 mem_load_enable_23 $end
$var wire 1 1 jump_enable_31 $end
$var wire 1 2 jump_enable_23 $end
$var wire 32 3 jump_address_31 [31:0] $end
$var wire 32 4 jump_address_23 [31:0] $end
$var wire 32 5 intruction_12 [31:0] $end
$var wire 32 6 imm_23 [31:0] $end
$var wire 2 7 debug [1:0] $end
$var wire 1 8 branch_enable_23 $end
$var wire 32 9 alu_res_34 [31:0] $end
$var wire 1 : alu_op_mod_23 $end
$var wire 3 ; alu_op_23 [2:0] $end
$var reg 1 < clk $end
$scope module s1 $end
$var wire 1 < clk $end
$var wire 32 = jump_address [31:0] $end
$var wire 1 1 jump_enable $end
$var wire 1 > stall $end
$var wire 32 ? next_address_wire [31:0] $end
$var wire 32 @ intruction_wire [31:0] $end
$var wire 32 A address [31:0] $end
$var reg 32 B instruction [31:0] $end
$var reg 32 C next_address [31:0] $end
$scope module imem $end
$var wire 32 D instruction_out [31:0] $end
$var wire 32 E address [31:0] $end
$var integer 32 F fd [31:0] $end
$var integer 32 G i [31:0] $end
$upscope $end
$scope module pc $end
$var wire 32 H address_out [31:0] $end
$var wire 1 < clk $end
$var wire 32 I jump_address [31:0] $end
$var wire 1 1 jump_enable $end
$var wire 32 J next_address_out [31:0] $end
$var reg 32 K pc [31:0] $end
$upscope $end
$upscope $end
$scope module s2 $end
$var wire 1 < clk $end
$var wire 32 L instruction [31:0] $end
$var wire 32 M pc [31:0] $end
$var wire 1 N stall $end
$var wire 32 O write_data [31:0] $end
$var wire 1 " write_enable $end
$var wire 5 P write_idx [4:0] $end
$var wire 32 Q rs2_val_wire [31:0] $end
$var wire 32 R rs1_val_wire [31:0] $end
$var wire 61 S decoded [60:0] $end
$var reg 1 T alu_op_mod $end
$var reg 1 U branch_enable $end
$var reg 32 V imm [31:0] $end
$var reg 32 W jump_address [31:0] $end
$var reg 1 2 jump_enable $end
$var reg 1 X mem_load_enable $end
$var reg 1 Y mem_store_enable $end
$var reg 5 Z rd_idx [4:0] $end
$var reg 1 [ reg_write_enable $end
$var reg 32 \ rs1_val [31:0] $end
$var reg 32 ] rs2_val [31:0] $end
$var reg 1 ^ use_imm $end
$var reg 3 _ alu_op [2:0] $end
$var reg 2 ` debug [1:0] $end
$scope module decode $end
$var wire 32 a instruction [31:0] $end
$var wire 61 b decoded_out [60:0] $end
$upscope $end
$scope module gpr $end
$var wire 1 < clk $end
$var wire 5 c read_idx_1 [4:0] $end
$var wire 5 d read_idx_2 [4:0] $end
$var wire 32 e write_data [31:0] $end
$var wire 1 " write_enable $end
$var wire 5 f write_idx [4:0] $end
$var wire 32 g read_data_2 [31:0] $end
$var wire 32 h read_data_1 [31:0] $end
$scope function read_gp_with_fwd $end
$var reg 5 i idx [4:0] $end
$upscope $end
$upscope $end
$upscope $end
$scope module s3 $end
$var wire 3 j alu_op [2:0] $end
$var wire 1 : alu_op_modified $end
$var wire 1 8 branch_enable $end
$var wire 1 < clk $end
$var wire 32 k imm [31:0] $end
$var wire 32 l jump_address [31:0] $end
$var wire 1 m jump_enable $end
$var wire 1 0 mem_load_enable $end
$var wire 1 . mem_store_enable $end
$var wire 5 n rd_idx [4:0] $end
$var wire 1 ) reg_write_enable $end
$var wire 32 o rs1_val [31:0] $end
$var wire 32 p rs2_val [31:0] $end
$var wire 1 q stall $end
$var wire 1 $ use_imm $end
$var wire 32 r alu_res [31:0] $end
$var reg 32 s alu_res_out [31:0] $end
$var reg 32 t jump_address_out [31:0] $end
$var reg 1 u jump_enable_out $end
$var reg 1 v mem_load_enable_out $end
$var reg 1 w mem_store_enable_out $end
$var reg 5 x rd_idx_out [4:0] $end
$var reg 1 y reg_write_enable_out $end
$var reg 32 z rs2_val_out [31:0] $end
$scope module alu $end
$var wire 32 { a [31:0] $end
$var wire 32 | b [31:0] $end
$var wire 1 : mod $end
$var wire 3 } op [2:0] $end
$var wire 32 ~ res_out [31:0] $end
$upscope $end
$upscope $end
$scope module s4 $end
$var wire 32 !" alu_res [31:0] $end
$var wire 1 < clk $end
$var wire 1 / mem_load_enable $end
$var wire 1 - mem_store_enable $end
$var wire 5 "" rd_idx [4:0] $end
$var wire 1 ( reg_write_enable $end
$var wire 32 #" rs2_val [31:0] $end
$var wire 1 $" stall $end
$var wire 32 %" mem_read_data [31:0] $end
$var reg 32 &" write_data_out [31:0] $end
$var reg 1 '" write_enable_out $end
$var reg 5 (" write_idx_out [4:0] $end
$scope module dmem $end
$var wire 1 < clk $end
$var wire 32 )" idx [31:0] $end
$var wire 32 *" write_data [31:0] $end
$var wire 1 - write_enable $end
$var wire 32 +" read_data_out [31:0] $end
$upscope $end
$upscope $end
$upscope $end
$enddefinitions $end
#0
$dumpvars
b10011100010000 +"
b0 *"
b0 )"
b0 ("
0'"
b0 &"
b10011100010000 %"
0$"
b0 #"
b0 ""
b0 !"
b0 ~
b0 }
b0 |
b0 {
b0 z
0y
b0 x
0w
0v
0u
b0 t
b0 s
b0 r
0q
b0 p
b0 o
b0 n
0m
b0 l
b0 k
b0 j
b0 i
b0 h
b0 g
b0 f
b0 e
b0 d
b0 c
b1000000000000000000000000000000000000010000 b
b10011000000000000000000000000 a
b0 `
b0 _
0^
b0 ]
b0 \
0[
b0 Z
0Y
0X
b0 W
b0 V
0U
0T
b1000000000000000000000000000000000000010000 S
b0 R
b0 Q
b0 P
b0 O
0N
b0 M
b10011000000000000000000000000 L
b0 K
b100 J
b0 I
b0 H
b101110100 G
b10000000000000000000000000000011 F
b0 E
b10011000000000000000000000000 D
b0 C
b10011000000000000000000000000 B
b0 A
b10011000000000000000000000000 @
b100 ?
0>
b0 =
0<
b0 ;
0:
b0 9
08
b0 7
b0 6
b10011000000000000000000000000 5
b0 4
b0 3
02
01
00
0/
0.
0-
b0 ,
b0 +
b0 *
0)
0(
b0 '
b0 &
b0 %
0$
b0 #
0"
b0 !
$end
#2
b1000 ?
b1000 J
b100 A
b100 E
b100 H
b100 K
1<
#4
b1000 ,
b1000 M
b1000 C
1)
1[
1$
1^
0<
#6
b10000011001000000000000000000000 @
b10000011001000000000000000000000 D
b1100 ?
b1100 J
b1000 A
b1000 E
b1000 H
b1000 K
1<
#8
b11000000000000000000000000000000000001010000 S
b11000000000000000000000000000000000001010000 b
1(
1y
b1000 4
b1000 l
b1000 W
b1100 ,
b1100 M
b1100 C
b10000011001000000000000000000000 5
b10000011001000000000000000000000 L
b10000011001000000000000000000000 a
b10000011001000000000000000000000 B
0<
#10
b11001000010100000000000000 @
b11001000010100000000000000 D
b10000 ?
b10000 J
b1100 A
b1100 E
b1100 H
b1100 K
1<
#12
b101000000000000000000000000000000001001010000 S
b101000000000000000000000000000000001001010000 b
b10000 ,
b10000 M
b10000 C
b11001000010100000000000000 5
b11001000010100000000000000 L
b11001000010100000000000000 a
b11001000010100000000000000 B
10
1X
b1100 4
b1100 l
b1100 W
b1 +
b1 n
b1 Z
b1000 3
b1000 =
b1000 I
b1000 t
1"
1'"
0<
#14
b10011000000000000000000000000 @
b10011000000000000000000000000 D
b10100 ?
b10100 J
b10000 A
b10000 E
b10000 H
b10000 K
1<
#16
b1000000000000000000000000000000000000010000 S
b1000000000000000000000000000000000000010000 b
b100 r
b100 ~
b100 |
b1100 3
b1100 =
b1100 I
b1100 t
1/
1v
b1 *
b1 ""
b1 x
b10100 4
b10100 l
b10100 W
b10 +
b10 n
b10 Z
b100 6
b100 k
b100 V
b10100 ,
b10100 M
b10100 C
b10011000000000000000000000000 5
b10011000000000000000000000000 L
b10011000000000000000000000000 a
b10011000000000000000000000000 B
0<
#18
b1100011100011100000000000010010 @
b1100011100011100000000000010010 D
b11000 ?
b11000 J
b10100 A
b10100 E
b10100 H
b10100 K
1<
#20
b10011100010000 R
b10011100010000 h
b1 i
b1 c
b100000000000010000000000000000000000001001111000000100 S
b100000000000010000000000000000000000001001111000000100 b
b0 r
b0 ~
b0 |
b1100100 %"
b1100100 +"
b11000 ,
b11000 M
b11000 C
b1100011100011100000000000010010 5
b1100011100011100000000000010010 L
b1100011100011100000000000010010 a
b1100011100011100000000000010010 B
00
0X
b0 +
b0 n
b0 Z
b0 6
b0 k
b0 V
b10100 3
b10100 =
b10100 I
b10100 t
b100 9
b100 !"
b100 )"
b100 s
b10 *
b10 ""
b10 x
b10011100010000 #
b10011100010000 O
b10011100010000 e
b10011100010000 &"
b1 !
b1 P
b1 f
b1 ("
0<
#22
b10011000000000000000000000000 @
b10011000000000000000000000000 D
b11100 ?
b11100 J
b11000 A
b11000 E
b11000 H
b11000 K
1<
#24
b0 R
b0 h
b0 i
b0 c
b1000000000000000000000000000000000000010000 S
b1000000000000000000000000000000000000010000 b
b10011100010000 %"
b10011100010000 +"
b10011100010000 r
b10011100010000 ~
b1100100 #
b1100100 O
b1100100 e
b1100100 &"
b10 !
b10 P
b10 f
b10 ("
b0 9
b0 !"
b0 )"
b0 s
0/
0v
b0 *
b0 ""
b0 x
0)
0[
18
1U
b101010100 4
b101010100 l
b101010100 W
0$
0^
b100111100 6
b100111100 k
b100111100 V
b10011100010000 '
b10011100010000 o
b10011100010000 {
b10011100010000 \
b11100 ,
b11100 M
b11100 C
b10011000000000000000000000000 5
b10011000000000000000000000000 L
b10011000000000000000000000000 a
b10011000000000000000000000000 B
0<
#26
b100000 ?
b100000 J
b11100 A
b11100 E
b11100 H
b11100 K
1<
#28
b0 r
b0 ~
b0 %"
b0 +"
b100000 ,
b100000 M
b100000 C
1)
1[
08
0U
b11100 4
b11100 l
b11100 W
1$
1^
b0 6
b0 k
b0 V
b0 '
b0 o
b0 {
b0 \
b101010100 3
b101010100 =
b101010100 I
b101010100 t
b10011100010000 9
b10011100010000 !"
b10011100010000 )"
b10011100010000 s
0(
0y
b0 #
b0 O
b0 e
b0 &"
b0 !
b0 P
b0 f
b0 ("
0<
#30
b1100011000011000000000100010000 @
b1100011000011000000000100010000 D
b100100 ?
b100100 J
b100000 A
b100000 E
b100000 H
b100000 K
1<
