memory/data_memory.sv
module DataMemory (
    input  Clock clk,
    input  Addr  idx,
    input  Data  write_data,
    input  Bool  write_enable,
    output Data  read_data_out
);
  DataReg mem[128:0];
  assign read_data_out = mem[idx[9:2]];

  initial begin
    mem[0] = `X1;
    mem[1] = `X2;
  end

  always @(posedge clk) begin
    if (write_enable == 1) begin
      mem[idx[9:2]] <= write_data;
      $display("MEM: write [%h]=%d", idx, write_data); // Needed to control proper functioning.
    end
  end
endmodule

pipeline/stage_4_mem.sv
module Stage4Mem(
    input Clock clk,
    input Data alu_res,
    input Data rs2_val,
    input RegId rd_idx,
    input Bool mem_load_enable,
    input Bool mem_store_enable,
    input Bool reg_write_enable,

    output BoolReg write_enable_out = FALSE,
    output RegIdReg write_idx_out = 'b0,
    output DataReg write_data_out = 'b0
);
    Data mem_read_data;

    DataMemory dmem(
        .clk(clk),
        .write_enable(mem_store_enable),
        .write_data(rs2_val),
        .idx(alu_res),
        .read_data_out(mem_read_data)
    );

    always @(posedge clk) begin
        write_enable_out <= reg_write_enable;
        write_idx_out <= rd_idx;
        write_data_out <= (mem_load_enable) ? mem_read_data : alu_res;
    end
endmodule

alu/alu.sv
module ALU (
    input Data a,
    input Data b,
    input ALUOp op,
    input Bool mod,    // Modifier: used for arithmetic shift
    output DataReg res_out
);
    assign res_out = alu(a, b, op, mod);

    // always @ (a, b, op, mod) begin
    //     $display("ALU: %h -> (%d %d) = %d", op, a, $signed(b), $signed(res_out));
    // end
endmodule

function Data alu(
    input Data a, b,
    input ALUOp op,
    input Bool mod
);
    case (op)
        ADD: alu = a + b;
        SLL: alu = a << b;
        SLT: alu = {{31{1'b0}}, $signed(a) < $signed(b)};
        SLTU: alu = {{31{1'b0}}, a < b};
        XOR: alu = a ^ b;
        SR: alu = (mod) ? (a >>> b) : (a >> b);
        OR: alu = a | b;
        AND: alu = a & b;
    endcase
endfunction

pipeline/stage_3_exec.sv
module Stage3Exec (
    input Clock clk,
    input ALUOp alu_op,
    input Bool  alu_op_modified,
    input Data  rs1_val,
    input Data  rs2_val,
    input Data  imm,
    input Bool  use_imm,
    input RegId rd_idx,
    input Bool  mem_store_enable,
    input Bool  mem_load_enable,
    input Bool  reg_write_enable,
    input Bool  jump_enable,
    input Bool  branch_enable,
    input Addr  jump_address,

    output DataReg  alu_res_out = 'b0,
    output DataReg  rs2_val_out = 'b0,
    output RegIdReg rd_idx_out = 'b0,
    output BoolReg  jump_enable_out = FALSE,
    output DataReg  jump_address_out = 'b0,
    output BoolReg  mem_store_enable_out = FALSE,
    output BoolReg  mem_load_enable_out = FALSE,
    output BoolReg  reg_write_enable_out = FALSE
);
  Data alu_res;

  ALU alu (
      .a      (rs1_val),
      .b      ((use_imm) ? imm : rs2_val),
      .op     (alu_op),
      .mod    (alu_op_modified),
      .res_out(alu_res)
  );

  always @(posedge clk) begin
    rd_idx_out <= rd_idx;
    rs2_val_out <= rs2_val;
    mem_load_enable_out <= mem_load_enable;
    mem_store_enable_out <= mem_store_enable;
    reg_write_enable_out <= reg_write_enable;
    alu_res_out <= alu_res;
    jump_enable_out <= (jump_enable || (branch_enable && (alu_op_modified ^ (alu_res == 'b0))));
    jump_address_out <= jump_address;
  end
endmodule

support/hazard_unit.sv
/**
 * Hazard unit to solve data hazards and stall after branches.
 * Structural hazerds are not handled and need to be handled via
 * duplication.
 */
module HazardUnit (
    input  Clock   clk,
    input  RegId   rs1,
    input  RegId   rs2,
    input  Bool    branch,
    input  RegId   rd,
    input  Bool    is_stall,
    output BoolReg stall_out = FALSE
);
  // We need at most 2 stall cycles stall. On branch, we stall next 2 cycles. 
  // On hazard detection, we stall this and the next cycle.
  // Branch may need both conditions. (Stalls before and after.)
  reg [1:0] counter = 'b0;
  // Check last to destinations to be compared with currently required data.
  // Request to zero registers are not a reason to stall, therefore zero
  // register can be used as neutral element here.
  RegIdReg current_rd = 'b0;
  RegIdReg last_rd = 'b0;
  RegIdReg prelast_rd = 'b0;

  always @(negedge clk) begin
    // If fetch is already stalled, the instruction data received were already
    // observed in previous cycle. Therefore we shall not evaluate them again
    // and we only count down the stall we are supposed to perform.
    if (~is_stall) begin
        if ((counter == 'd2) ||
            ((current_rd != 'b0) && ((rs1 == current_rd) || (rs2 == current_rd)))) begin
            // Ppending 2 cycle stall or dependency on the last instruction.
            counter <= 'd1;
            stall_out <= TRUE;
        end
        else if ((counter == 'd1) ||
            ((last_rd != 'b0) && ((rs1 == last_rd) || (rs2 == last_rd)))) begin
            // Pendning 1 stall or dependency on prelast.
            counter <= 'd0;
            stall_out <= TRUE;
        end else
        if (branch) begin
            // Execute branch and schedule 2 stalls.
            counter <= 'd2;
            stall_out <= FALSE;
        end else begin
            // Countdown ended, can execute again.
            stall_out <= FALSE;
        end
    end else begin
      // Evaluate the already accumulated stalls.
      if (counter == 'd2) begin
        counter <= 'd1;
        stall_out <= TRUE;
      end if (counter == 'd1) begin
        counter <= 'd0;
        stall_out <= TRUE;
      end else begin
        // Countdown ended, can execute again.

        // If branch has also dependency, the above code will not get triggered as
        // branch. We need to detect it here.
        if (branch) begin
            counter <= 'd2;
        end
        stall_out <= FALSE;
      end
    end

    // Shift the history of destionation regs.
    prelast_rd <= last_rd;
    last_rd <= current_rd;
    current_rd <= rd;
  end
endmodule

register/gp_register_file.sv
module GPRegisterFile(
    input Clock clk,
    input RegId read_idx_1,
    input RegId read_idx_2,
    input RegId write_idx,
    input Data write_data,
    input Bool write_enable,
    output Data read_data_1_out,
    output Data read_data_2_out
);
    DataReg gp[31:0];

    assign read_data_1_out = read_gp_with_fwd(read_idx_1);
    assign read_data_2_out = read_gp_with_fwd(read_idx_2);

    always @ (posedge clk) begin
        if (write_enable) begin
            if (write_idx != 0) gp[write_idx] <= write_data;
            // $display("REG: r1=%h r2=%h w[%d]=%h", gp[1], gp[2], write_idx, write_data);
        end
    end

    function Data read_gp_with_fwd(
        input RegId read_idx
    );
        if (read_idx == 0)
            read_gp_with_fwd = 'b0;
        else if (write_enable && read_idx == write_idx)
            read_gp_with_fwd = write_data;
        else
            read_gp_with_fwd = gp[read_idx];
    endfunction
endmodule

decode/decode.sv
module Decode(
    input Instr            instruction,
    output DecodeOutput    decoded_out
);    
    // Byteswap to fit specification description
    assign decoded_out = decode(parse(byteswap(instruction)));
endmodule

function bit[31:0] byteswap(input bit[31:0] x);
    byteswap = {x[7:0], x[15:8], x[23:16], x[31:24]};
endfunction

function ParsedInstruction parse(input Instr intruction);
    parse.opcode   = intruction[6:2];       // Assuming only 32bit instruction support
    parse.rd       = intruction[11:7];
    parse.funct3   = intruction[14:12];
    parse.rs1      = intruction[19:15];
    parse.rs2      = intruction[24:20];
    parse.funct7   = intruction[31:25];
    parse.imm_sign = intruction[31];
    parse.I_imm    = {{20{parse.imm_sign}}, parse.funct7, parse.rs2};
    parse.S_imm    = {{20{parse.imm_sign}}, parse.funct7, parse.rd};
    parse.U_imm    = {{12{parse.imm_sign}}, parse.funct7, parse.rs2, parse.rs1, parse.funct3};
    parse.B_imm    = {{20{parse.imm_sign}}, parse.imm_sign, intruction[7], intruction[30:25], intruction[11:8]};
    parse.J_imm    = {{13{parse.imm_sign}}, parse.rs1, parse.funct3, intruction[20], intruction[30:21]};
endfunction

function DecodeOutput decode(input ParsedInstruction i);
    decode = 61'bx;

    case (i.opcode)
        OP: begin
            decode.alu_rs1 = i.rs1;
            decode.alu_rs2 = i.rs2;
            decode.alu_rd = i.rd;
            decode.alu_op = i.funct3;
            decode.alu_use_imm = FALSE;
            decode.alu_rs1_pc = FALSE;
            decode.alu_rs2_neg = (i.funct3 == 'b0 && i.funct7 == 'd32); // Subtraction
            decode.alu_op_mod = FALSE;
            decode.imm = `NONE;
            decode.mem_load = FALSE;
            decode.mem_store = FALSE;
            decode.reg_write = TRUE;
            decode.jump_enable = FALSE;
            decode.branch_enable = FALSE;
            decode.debug = OK;
            $display("DEC: ALURegOp %h (%h <= %h %h)", i.funct3, i.rd, i.rs1, i.rs2);
        end
        OP_IMM: begin
            decode.alu_rs1 = i.rs1;
            decode.alu_rs2 = 'b0;
            decode.alu_rd = i.rd;
            decode.alu_op = i.funct3;
            decode.alu_use_imm = TRUE;
            decode.alu_rs1_pc = FALSE;
            decode.alu_rs2_neg = (i.funct3 == 'b0 && i.funct7 == 'd32); // Subtraction
            decode.alu_op_mod = FALSE;
            decode.imm = i.I_imm;
            decode.mem_load = FALSE;
            decode.mem_store = FALSE;
            decode.reg_write = TRUE;
            decode.jump_enable = FALSE;
            decode.branch_enable = FALSE;
            decode.debug = OK;
            $display("DEC: ALUImmOp %h (%h <= %h %h)", i.funct3, i.rd, i.rs1, i.I_imm);
        end
        LOAD: begin
            decode.alu_rs1 = i.rs1;
            decode.alu_rs2 = 'b0;
            decode.alu_rd = i.rd;
            decode.alu_op = 'h0;
            decode.alu_use_imm = TRUE;
            decode.alu_rs1_pc = FALSE;
            decode.alu_rs2_neg = FALSE;
            decode.alu_op_mod = FALSE;
            decode.imm = i.I_imm;
            decode.mem_load = TRUE;
            decode.mem_store = FALSE;
            decode.reg_write = TRUE;
            decode.jump_enable = FALSE;
            decode.branch_enable = FALSE;
            decode.debug = OK;
            $display("DEC: Load %h => %h+%h", i.rd, i.rs1, i.I_imm);
        end
        STORE: begin
            decode.alu_rs1 = i.rs1;
            decode.alu_rs2 = i.rs2;
            decode.alu_rd = i.rd;
            decode.alu_op = 'h0;
            decode.alu_use_imm = TRUE;
            decode.alu_rs1_pc = FALSE;
            decode.alu_rs2_neg = FALSE;
            decode.alu_op_mod = FALSE;
            decode.imm = i.S_imm;    // Offset to rs1
            decode.mem_load = FALSE;
            decode.mem_store = TRUE;
            decode.reg_write = FALSE;
            decode.jump_enable = FALSE;
            decode.branch_enable = FALSE;
            decode.debug = OK;
            $display("DEC: Store %h => %h+%h", i.rs2, i.rs1, i.I_imm);
        end
        JAL: begin
            decode.alu_rs1 = 'b0;
            decode.alu_rs2 = 'b0;
            decode.alu_rd = i.rd;
            decode.alu_op = 'h4;
            decode.alu_use_imm = FALSE;
            decode.alu_rs1_pc = TRUE;
            decode.alu_rs2_neg = FALSE;
            decode.alu_op_mod = FALSE;
            decode.imm = i.J_imm << 1;
            decode.mem_load = FALSE;
            decode.mem_store = FALSE;
            decode.reg_write = TRUE;
            decode.jump_enable = TRUE;
            decode.branch_enable = FALSE;
            decode.debug = OK;
            $display("DEC: Jump %h, %d", i.J_imm, $signed(i.J_imm));
        end
        BRANCH: begin
            decode.alu_rs1 = i.rs1;
            decode.alu_rs2 = i.rs2;
            decode.alu_rd = 'h0;
            decode.alu_op = {1'b0, i.funct3[2:1]};
            decode.alu_rs2_neg = ~i.funct3[2];
            decode.alu_op_mod = i.funct3[0];
            decode.alu_use_imm = FALSE;
            decode.alu_rs1_pc = FALSE;
            decode.imm = i.B_imm << 1;
            decode.mem_load = FALSE;
            decode.mem_store = FALSE;
            decode.reg_write = FALSE;
            decode.jump_enable = FALSE;
            decode.branch_enable = TRUE;
            decode.debug = OK;
            $display("DEC: Branch by %h", $signed(i.B_imm << 1));
        end
        SYSTEM: begin
            decode.alu_rs1 = 'b0;
            decode.alu_rs2 = 'b0;
            decode.alu_rd = 'b0;
            decode.alu_rs1_pc = FALSE;
            decode.alu_op_mod = FALSE;
            decode.reg_write = FALSE;
            decode.jump_enable = FALSE;
            decode.branch_enable = FALSE;
            case ({i.funct7, i.rs2, i.rs1, i.funct3, i.rd})
                25'b0000000_00001_00000_000_00000: decode.debug = BREAK;
                default: decode.debug = FAIL;
            endcase
            $display("DEC: System instruction invoked");
        end
        default: begin
            decode.alu_rs1 = 'b0;
            decode.alu_rs2 = 'b0;
            decode.alu_rd = 'b0;
            decode.alu_rs1_pc = FALSE;
            decode.alu_op_mod = FALSE;
            decode.reg_write = FALSE;
            decode.jump_enable = FALSE;
            decode.branch_enable = FALSE;
            decode.debug = FAIL;
            $display("DEC: Unknown instruction");
        end
    endcase
endfunction

pipeline/stage_2_decode.sv
module Stage2Decode (
    input  Clock       clk,
    input  Data        instruction,
    input  Data        pc,
    input  Bool        write_enable,
    input  RegId       write_idx,
    input  Data        write_data,
    output ALUOpReg    alu_op_out = 'b0,
    output DataReg     rs1_val_out = 'b0,
    output DataReg     rs2_val_out = 'b0,
    output DataReg     imm_out = 'b0,
    output BoolReg     use_imm_out = FALSE,
    output RegIdReg    rd_idx_out = 'b0,
    output BoolReg     alu_op_mod_out = FALSE,
    output BoolReg     mem_load_enable_out = FALSE,
    output BoolReg     mem_store_enable_out = FALSE,
    output BoolReg     jump_enable_out = FALSE,
    output BoolReg     branch_enable_out = FALSE,
    output BoolReg     reg_write_enable_out = FALSE,
    output AddrReg     jump_address_out = 'b0,
    output BoolReg     should_stall_s1_out = FALSE,
    output DebugStatus debug_out = OK
);
  Data rs1_val_wire, rs2_val_wire;
  DecodeOutput decoded;

  Decode decode (
      .instruction(instruction),
      .decoded_out(decoded)
  );

  GPRegisterFile gpr (
      .clk            (clk),
      .read_idx_1     (decoded.alu_rs1),
      .read_idx_2     (decoded.alu_rs2),
      .write_enable   (write_enable),
      .write_idx      (write_idx),
      .write_data     (write_data),
      .read_data_1_out(rs1_val_wire),
      .read_data_2_out(rs2_val_wire)
  );

  Bool should_stall = FALSE;

  HazardUnit hz (
      .clk      (clk),
      .rs1      (decoded.alu_rs1),
      .rs2      (decoded.alu_rs2),
      .rd       (decoded.alu_rd),
      .branch   (decoded.jump_enable | decoded.branch_enable),
      .is_stall (should_stall_s1_out),
      .stall_out () // TODO (should_stall)
  );

  always @(posedge clk) begin
    alu_op_out <= (should_stall) ? ADD : decoded.alu_op;
    rs1_val_out <= (should_stall) ? 'b0 : ((decoded.alu_rs1_pc) ? pc : rs1_val_wire);
    rs2_val_out <= (should_stall) ? 'b0 : ((decoded.alu_rs2_neg) ? -rs2_val_wire : rs2_val_wire);
    imm_out <= decoded.imm;
    use_imm_out <= (should_stall) ? FALSE : decoded.alu_use_imm;
    rd_idx_out <= (should_stall) ? 'b0 : decoded.alu_rd;
    alu_op_mod_out <= (should_stall) ? FALSE : decoded.alu_op_mod;
    jump_address_out <= pc + $signed(decoded.imm);
    jump_enable_out <= (should_stall) ? FALSE : decoded.jump_enable;
    branch_enable_out <= (should_stall) ? FALSE : decoded.branch_enable;
    reg_write_enable_out <= (should_stall) ? FALSE : decoded.reg_write;
    mem_load_enable_out <= (should_stall) ? FALSE : decoded.mem_load;
    mem_store_enable_out <= (should_stall) ? FALSE : decoded.mem_store;
    should_stall_s1_out <= should_stall;
    debug_out <= (should_stall) ? OK : decoded.debug;

    if (should_stall) $display("STALL");
  end
endmodule

memory/instruction_memory.sv
module InstructionMemory(
    input Addr address,
    output Addr instruction_out
);
    DataReg mem[128:0];
    integer fd, i;

    assign instruction_out = mem[address[9:2]];

    initial begin
        fd = $fopen("gcd.bin","rb");
        i = $fread(mem, fd);
        $fclose(fd);
    end
endmodule

register/program_counter.sv
module ProgramCounter(
    input Clock clk,
    input Bool stall,
    input Bool jump_enable,
    input Addr jump_address,
    output AddrReg pc_out = 'b0
);    
    always @ (negedge clk) begin
        pc_out <= (jump_enable) ? jump_address : pc_out + 'd4;
        // $display("====================================================");
        // $display("PC: 0x%h [jump=%h]", (jump_enable) ? jump_address : next_address_out, jump_enable);
    end

endmodule

pipeline/stage_1_fetch.sv
module Stage1Fetch(
    input Clock clk,
    input Bool stall,
    input Bool jump_enable,
    input Addr jump_address,
    output InstrReg instruction_out = `NOP,
    output AddrReg pc_out = 'b0
);
    Addr pc_wire;
    Instr intruction_wire;

    ProgramCounter pc(
        .clk(clk),
        .stall(stall),
        .jump_enable(jump_enable),
        .jump_address(jump_address),
        .pc_out(pc_wire)
    );

    InstructionMemory imem(
        .address(pc_wire),
        .instruction_out(intruction_wire)
    );

    always @(posedge clk) begin
        instruction_out <= intruction_wire;
        pc_out <= pc_wire;
    end

endmodule

test_pipeline_cpu.sv
typedef bit [31:0] Data;
typedef reg [31:0] DataReg;
typedef bit [0:0] Clock;
typedef reg [0:0] ClockReg;
typedef bit [31:0] Addr;
typedef reg [31:0] AddrReg;
typedef bit [31:0] Instr;
typedef reg [31:0] InstrReg;
typedef bit [4:0] RegId;
typedef reg [4:0] RegIdReg;

enum bit [4:0] {
  OP = 'b01100,
  OP_IMM = 'b00100,
  SYSTEM = 'b11100,
  LOAD = 'b00000,
  STORE = 'b01000,
  JAL = 'b11011,
  BRANCH = 'b11000
} Opcode;

typedef enum bit [2:0] {
  ADD = 'h0,
  SLL = 'h1,
  SLT = 'h2,
  SLTU = 'h3,
  XOR = 'h4,
  SR = 'h5,
  OR = 'h6,
  AND = 'h7
} ALUOp;

typedef bit [2:0] ALUOpReg;

typedef enum bit [1:0] {
  OK = 2'b00,
  BREAK = 2'b01,
  FAIL = 2'b10
} DebugStatus;

typedef enum bit [0:0] {
  FALSE = 1'b0,
  TRUE = 1'b1
} Bool;

typedef reg [0:0] BoolReg;

typedef struct packed {
  ALUOp alu_op;
  RegId alu_rs1;
  RegId alu_rs2;
  RegId alu_rd;
  Bool alu_use_imm;
  Bool alu_rs1_pc;
  Bool alu_rs2_neg;
  Bool alu_op_mod;
  Data imm;
  Bool mem_load;
  Bool mem_store;
  Bool reg_write;
  Bool jump_enable;
  Bool branch_enable;
  DebugStatus debug;
} DecodeOutput;

`define NONE 'bx
`define NOP 'b0010011000000000000000000000000

typedef struct packed {
  bit [4:0] opcode;
  bit [6:0] funct7;
  bit [2:0] funct3;
  bit [4:0] rs1, rs2, rd;
  bit [0:0] imm_sign;
  bit [31:0] I_imm, S_imm, U_imm, B_imm, J_imm;
} ParsedInstruction;

module test ();
  ClockReg clk;

  // 1 -> 2
  wire Instr intruction_12;
  wire Addr next_address_12;
  // 3 -> 1
  wire Bool jump_enable_31;
  wire Addr jump_address_31;
  // 2 -> 1
  Bool should_stall_s1;

  Stage1Fetch s1 (
      .clk         (clk),
      .stall       (should_stall_s1),
      // 1 -> 2
      .instruction_out (intruction_12),
      .pc_out(next_address_12),
      .jump_enable (jump_enable_31),
      .jump_address(jump_address_31)
  );

  // 2 -> 3
  wire Data rs1_val_23, rs2_val_23, imm_23;
  wire RegId rd_idx_23;
  wire ALUOp alu_op_23;
  wire Bool use_imm_23, alu_op_mod_23, mem_load_enable_23, mem_store_enable_23,
      reg_write_enable_23, branch_enable_23, jump_enable_23;
  wire Addr jump_address_23;
  // 4 -> 2
  wire Data write_data_42;
  wire RegId write_idx_42;
  wire Bool write_enable_42;

  wire DebugStatus debug;

  Stage2Decode s2 (
      .clk             (clk),
      // 1 -> 2
      .instruction     (intruction_12),
      .pc              (next_address_12),
      //_out 2 -> 3
      .alu_op_out          (alu_op_23),
      .rs1_val_out         (rs1_val_23),
      .rs2_val_out         (rs2_val_23),
      .rd_idx_out          (rd_idx_23),
      .imm_out             (imm_23),
      .use_imm_out         (use_imm_23),
      .alu_op_mod_out      (alu_op_mod_23),
      .mem_load_enable_out (mem_load_enable_23),
      .mem_store_enable_out(mem_store_enable_23),
      .reg_write_enable_out(reg_write_enable_23),
      .jump_enable_out     (jump_enable_23),
      .branch_enable_out   (branch_enable_23),
      .jump_address_out    (jump_address_23),
      // 4 -> 2
      .write_data      (write_data_42),
      .write_idx       (write_idx_42),
      .write_enable    (write_enable_42),

      .debug_out(debug),
      .should_stall_s1_out(should_stall_s1)
  );

  // 3 -> 4
  wire Data alu_res_34, rs2_val_34;
  wire RegId rd_idx_34;
  wire Bool mem_store_enable_34, mem_load_enable_34, reg_write_enable_34;

  Stage3Exec s3 (
      .clk                 (clk),
      // 2 -> 3
      .alu_op              (alu_op_23),
      .rs1_val             (rs1_val_23),
      .rs2_val             (rs2_val_23),
      .imm                 (imm_23),
      .rd_idx              (rd_idx_23),
      .alu_op_modified     (alu_op_mod_23),
      .use_imm             (use_imm_23),
      .reg_write_enable    (reg_write_enable_23),
      .mem_load_enable     (mem_load_enable_23),
      .mem_store_enable    (mem_store_enable_23),
      .jump_enable         (jump_enable_23),
      .jump_address        (jump_address_23),
      .branch_enable       (branch_enable_23),
      // 3 -> 4
      .alu_res_out         (alu_res_34),
      .rs2_val_out         (rs2_val_34),
      .rd_idx_out          (rd_idx_34),
      .reg_write_enable_out(reg_write_enable_34),
      .mem_load_enable_out (mem_load_enable_34),
      .mem_store_enable_out(mem_store_enable_34),
      .jump_enable_out     (jump_enable_31),
      .jump_address_out    (jump_address_31)
  );

  Stage4Mem s4 (
      .clk             (clk),
      // 3 -> 4
      .alu_res         (alu_res_34),
      .rs2_val         (rs2_val_34),
      .rd_idx          (rd_idx_34),
      .reg_write_enable(reg_write_enable_34),
      .mem_load_enable (mem_load_enable_34),
      .mem_store_enable(mem_store_enable_34),
      // 4 -> 2
      .write_enable_out(write_enable_42),
      .write_idx_out   (write_idx_42),
      .write_data_out  (write_data_42)
  );


  always @(debug) begin
    case (debug)
      'b01: begin
        $display("Breakpoint reached");
        $finish;
      end
      'b10: begin
        $display("Illegal instruction - teminating");
        $finish;
      end
    endcase
  end

  initial begin
    $dumpfile("test.vcd");
    $dumpvars;
    clk = 0;
  end

  always #2 begin
    clk = ~clk;
  end
  always #10000 $finish; // Terminate the program in case of infinite loop
endmodule

test.vcd
$date
	Fri Jan  8 21:27:13 2021
$end
$version
	Icarus Verilog
$end
$timescale
	1s
$end
$scope module test $end
$var wire 5 ! write_idx_42 [4:0] $end
$var wire 1 " write_enable_42 $end
$var wire 32 # write_data_42 [31:0] $end
$var wire 1 $ use_imm_23 $end
$var wire 1 % should_stall_s1 $end
$var wire 32 & rs2_val_34 [31:0] $end
$var wire 32 ' rs2_val_23 [31:0] $end
$var wire 32 ( rs1_val_23 [31:0] $end
$var wire 1 ) reg_write_enable_34 $end
$var wire 1 * reg_write_enable_23 $end
$var wire 5 + rd_idx_34 [4:0] $end
$var wire 5 , rd_idx_23 [4:0] $end
$var wire 32 - next_address_12 [31:0] $end
$var wire 1 . mem_store_enable_34 $end
$var wire 1 / mem_store_enable_23 $end
$var wire 1 0 mem_load_enable_34 $end
$var wire 1 1 mem_load_enable_23 $end
$var wire 1 2 jump_enable_31 $end
$var wire 1 3 jump_enable_23 $end
$var wire 32 4 jump_address_31 [31:0] $end
$var wire 32 5 jump_address_23 [31:0] $end
$var wire 32 6 intruction_12 [31:0] $end
$var wire 32 7 imm_23 [31:0] $end
$var wire 2 8 debug [1:0] $end
$var wire 1 9 branch_enable_23 $end
$var wire 32 : alu_res_34 [31:0] $end
$var wire 1 ; alu_op_mod_23 $end
$var wire 3 < alu_op_23 [2:0] $end
$var reg 1 = clk $end
$scope module s1 $end
$var wire 1 > clk $end
$var wire 32 ? jump_address [31:0] $end
$var wire 1 2 jump_enable $end
$var wire 1 % stall $end
$var wire 32 @ pc_wire [31:0] $end
$var wire 32 A intruction_wire [31:0] $end
$var reg 32 B instruction_out [31:0] $end
$var reg 32 C pc_out [31:0] $end
$scope module imem $end
$var wire 32 D address [31:0] $end
$var wire 32 E instruction_out [31:0] $end
$var integer 32 F fd [31:0] $end
$var integer 32 G i [31:0] $end
$upscope $end
$scope module pc $end
$var wire 1 > clk $end
$var wire 32 H jump_address [31:0] $end
$var wire 1 2 jump_enable $end
$var wire 1 % stall $end
$var reg 32 I pc_out [31:0] $end
$upscope $end
$upscope $end
$scope module s2 $end
$var wire 1 J clk $end
$var wire 32 K instruction [31:0] $end
$var wire 32 L pc [31:0] $end
$var wire 32 M write_data [31:0] $end
$var wire 1 " write_enable $end
$var wire 5 N write_idx [4:0] $end
$var wire 32 O rs2_val_wire [31:0] $end
$var wire 32 P rs1_val_wire [31:0] $end
$var wire 61 Q decoded [60:0] $end
$var reg 1 R alu_op_mod_out $end
$var reg 1 S branch_enable_out $end
$var reg 32 T imm_out [31:0] $end
$var reg 32 U jump_address_out [31:0] $end
$var reg 1 V jump_enable_out $end
$var reg 1 W mem_load_enable_out $end
$var reg 1 X mem_store_enable_out $end
$var reg 5 Y rd_idx_out [4:0] $end
$var reg 1 Z reg_write_enable_out $end
$var reg 32 [ rs1_val_out [31:0] $end
$var reg 32 \ rs2_val_out [31:0] $end
$var reg 1 ] should_stall_s1_out $end
$var reg 1 ^ use_imm_out $end
$var reg 3 _ alu_op_out [2:0] $end
$var reg 2 ` debug_out [1:0] $end
$var reg 1 a should_stall $end
$scope module decode $end
$var wire 32 b instruction [31:0] $end
$var wire 61 c decoded_out [60:0] $end
$upscope $end
$scope module gpr $end
$var wire 1 J clk $end
$var wire 5 d read_idx_1 [4:0] $end
$var wire 5 e read_idx_2 [4:0] $end
$var wire 32 f write_data [31:0] $end
$var wire 1 " write_enable $end
$var wire 5 g write_idx [4:0] $end
$var wire 32 h read_data_2_out [31:0] $end
$var wire 32 i read_data_1_out [31:0] $end
$scope function read_gp_with_fwd $end
$var reg 5 j read_idx [4:0] $end
$upscope $end
$upscope $end
$scope module hz $end
$var wire 1 k branch $end
$var wire 1 J clk $end
$var wire 1 l is_stall $end
$var wire 5 m rd [4:0] $end
$var wire 5 n rs1 [4:0] $end
$var wire 5 o rs2 [4:0] $end
$var reg 2 p counter [1:0] $end
$var reg 5 q current_rd [4:0] $end
$var reg 5 r last_rd [4:0] $end
$var reg 5 s prelast_rd [4:0] $end
$var reg 1 t stall_out $end
$upscope $end
$upscope $end
$scope module s3 $end
$var wire 3 u alu_op [2:0] $end
$var wire 1 ; alu_op_modified $end
$var wire 1 9 branch_enable $end
$var wire 1 v clk $end
$var wire 32 w imm [31:0] $end
$var wire 32 x jump_address [31:0] $end
$var wire 1 3 jump_enable $end
$var wire 1 1 mem_load_enable $end
$var wire 1 / mem_store_enable $end
$var wire 5 y rd_idx [4:0] $end
$var wire 1 * reg_write_enable $end
$var wire 32 z rs1_val [31:0] $end
$var wire 32 { rs2_val [31:0] $end
$var wire 1 $ use_imm $end
$var wire 32 | alu_res [31:0] $end
$var reg 32 } alu_res_out [31:0] $end
$var reg 32 ~ jump_address_out [31:0] $end
$var reg 1 !" jump_enable_out $end
$var reg 1 "" mem_load_enable_out $end
$var reg 1 #" mem_store_enable_out $end
$var reg 5 $" rd_idx_out [4:0] $end
$var reg 1 %" reg_write_enable_out $end
$var reg 32 &" rs2_val_out [31:0] $end
$scope module alu $end
$var wire 32 '" a [31:0] $end
$var wire 32 (" b [31:0] $end
$var wire 1 ; mod $end
$var wire 3 )" op [2:0] $end
$var wire 32 *" res_out [31:0] $end
$upscope $end
$upscope $end
$scope module s4 $end
$var wire 32 +" alu_res [31:0] $end
$var wire 1 ," clk $end
$var wire 1 0 mem_load_enable $end
$var wire 1 . mem_store_enable $end
$var wire 5 -" rd_idx [4:0] $end
$var wire 1 ) reg_write_enable $end
$var wire 32 ." rs2_val [31:0] $end
$var wire 32 /" mem_read_data [31:0] $end
$var reg 32 0" write_data_out [31:0] $end
$var reg 1 1" write_enable_out $end
$var reg 5 2" write_idx_out [4:0] $end
$scope module dmem $end
$var wire 1 ," clk $end
$var wire 32 3" idx [31:0] $end
$var wire 32 4" write_data [31:0] $end
$var wire 1 . write_enable $end
$var wire 32 5" read_data_out [31:0] $end
$upscope $end
$upscope $end
$upscope $end
$enddefinitions $end
#0
$dumpvars
b1110110001000000 5"
b0 4"
b0 3"
b0 2"
01"
b0 0"
b1110110001000000 /"
b0 ."
b0 -"
0,"
b0 +"
b0 *"
b0 )"
b0 ("
b0 '"
b0 &"
0%"
b0 $"
0#"
0""
0!"
b0 ~
b0 }
b0 |
b0 {
b0 z
b0 y
b0 x
b0 w
0v
b0 u
0t
b0 s
b0 r
b0 q
b0 p
b0 o
b0 n
b0 m
0l
0k
b0 j
b0 i
b0 h
b0 g
b0 f
b0 e
b0 d
b1000000000000000000000000000000000000010000 c
b10011000000000000000000000000 b
0a
b0 `
b0 _
0^
0]
b0 \
b0 [
0Z
b0 Y
0X
0W
0V
b0 U
b0 T
0S
0R
b1000000000000000000000000000000000000010000 Q
b0 P
b0 O
b0 N
b0 M
b0 L
b10011000000000000000000000000 K
0J
b0 I
b0 H
b110010000 G
b10000000000000000000000000000011 F
b10011000000000000000000000000 E
b0 D
b0 C
b10011000000000000000000000000 B
b10011000000000000000000000000 A
b0 @
b0 ?
0>
0=
b0 <
0;
b0 :
09
b0 8
b0 7
b10011000000000000000000000000 6
b0 5
b0 4
03
02
01
00
0/
0.
b0 -
b0 ,
b0 +
0*
0)
b0 (
b0 '
b0 &
0%
0$
b0 #
0"
b0 !
$end
#2
1*
1Z
1$
1^
1>
1J
1v
1,"
1=
#4
b100 @
b100 D
b100 I
0>
0J
0v
0,"
0=
#6
b100 -
b100 L
b100 C
1)
1%"
1>
1J
1v
1,"
1=
#8
b1000 @
b1000 D
b1000 I
0>
0J
0v
0,"
0=
#10
b1000 -
b1000 L
b1000 C
b100 5
b100 x
b100 U
1"
11"
1>
1J
1v
1,"
1=
#12
b10000011001000000000000000000000 A
b10000011001000000000000000000000 E
b1100 @
b1100 D
b1100 I
0>
0J
0v
0,"
0=
#14
b1 m
b11000000000000000000000000000000000001010000 Q
b11000000000000000000000000000000000001010000 c
b1100 -
b1100 L
b1100 C
b10000011001000000000000000000000 6
b10000011001000000000000000000000 K
b10000011001000000000000000000000 b
b10000011001000000000000000000000 B
b1000 5
b1000 x
b1000 U
b100 4
b100 ?
b100 H
b100 ~
1>
1J
1v
1,"
1=
#16
b11001000010100000000000000 A
b11001000010100000000000000 E
b10000 @
b10000 D
b10000 I
b1 q
0>
0J
0v
0,"
0=
